habsim/__init__.py
habsim/classes.py
habsim/ioutil.py
habsim/util.py
habsim-0.2.dist-info/LICENSE
habsim-0.2.dist-info/METADATA
habsim-0.2.dist-info/WHEEL
habsim-0.2.dist-info/top_level.txt
habsim-0.2.dist-info/RECORD
