Metadata-Version: 2.1
Name: habsim
Version: 0.2
Summary: Client interface to Stanford Student Space Initiative HABSIM server
Home-page: http://github.com/stanford-ssi/habsim_client
License: GNU GPLv3
Platform: UNKNOWN
Requires-Python: >=3
